{
  "gitSyncId": "668ff84389b1a8028a70bcb5_3fe1bfb3-d35c-4c71-8e1a-615d96f8097b",
  "id": "Login_createUser",
  "pluginId": "mysql-plugin",
  "pluginType": "DB",
  "unpublishedAction": {
    "actionConfiguration": {
      "body": "# // Daniel T. K. W. - github.com/danieltkw - danielkopolo95@gmail.com\n# // ------------------------------------------------------------\n# createUser - Login\n\nINSERT INTO `public_user_auth` (`first_name`, `last_name`, `email`, `username`, `password_hash`, `last_login`, `role`, `created`, `updated`)\nVALUES ('{{inp_firstName.text}}', '{{inp_lastName.text}}', '{{inp_registerEmail.text}}', '{{inp_registerEmail.text}}', '{{this.params.passwordHash}}', NOW(), 'Admin', NOW(), NOW());\n\n# // ------------------------------------------------------------\n",
      "encodeParamsToggle": true,
      "paginationType": "NONE",
      "pluginSpecifiedTemplates": [
        {
          "value": true
        }
      ],
      "timeoutInMillisecond": 10000
    },
    "confirmBeforeExecute": false,
    "datasource": {
      "id": "appsmith_dba",
      "isAutoGenerated": false,
      "name": "appsmith_dba",
      "pluginId": "mysql-plugin"
    },
    "dynamicBindingPathList": [
      {
        "key": "body"
      }
    ],
    "executeOnLoad": false,
    "name": "createUser",
    "pageId": "Login",
    "userSetOnLoad": false
  }
}